swimlane_migrator/__init__.py
swimlane_migrator/utils.py
swimlane_migrator/containers/__init__.py
swimlane_migrator/containers/server.py
swimlane_migrator/fields/__init__.py
swimlane_migrator/fields/core.py
swimlane_migrator/fields/types/__init__.py
swimlane_migrator/fields/types/cross_reference.py
swimlane_migrator/fields/types/usergroups.py
swimlane_migrator/fields/types/valuelist.py
swimlane_migrator/fields/types/base/__init__.py
swimlane_migrator/fields/types/base/fields.py
swimlane_migrator/layouts/__init__.py
swimlane_migrator/layouts/core.py
swimlane_migrator/layouts/tasks/__init__.py
swimlane_migrator/layouts/tasks/core.py
swimlane_migrator/layouts/types/__init__.py
swimlane_migrator/layouts/types/integration.py
swimlane_migrator/layouts/types/base/__init__.py
swimlane_migrator/layouts/types/base/layouts.py
swimlane_migrator/usergroups/__init__.py
swimlane_migrator/usergroups/groups.py
swimlane_migrator/usergroups/role.py
swimlane_migrator/workflow/__init__.py
swimlane_migrator/workflow/core.py
swimlane_migrator/workspaces/__init__.py
swimlane_migrator/workspaces/dashboards.py
swimlane_migrator/workspaces/reports.py
swimlane_migrator/workspaces/workspaces.py
swimlane_migrator-0.5.6.dist-info/METADATA
swimlane_migrator-0.5.6.dist-info/WHEEL
swimlane_migrator-0.5.6.dist-info/top_level.txt
swimlane_migrator-0.5.6.dist-info/RECORD
