Metadata-Version: 2.1
Name: swimlane-migrator
Version: 0.5.6
Summary: Swimlane Content Migration Package
Home-page: https://swimlane.com
Author: Swimlane
Author-email: info@swimlane.com
License: UNKNOWN
Platform: UNKNOWN
Requires-Dist: swimlane (<11.0,>=3.0)
Requires-Dist: pymongo (>=3.12.0)
